MIMICEmbedding/__init__.py
MIMICEmbedding/combination_util.py
MIMICEmbedding/cxr_preproc.py
MIMICEmbedding/ecg_preproc.py
MIMICEmbedding/ecg_signal_embedding_extraction.py
MIMICEmbedding/echo_preproc.py
MIMICEmbedding/icd_cohort_combined_searching.py
MIMICEmbedding/image_embeddings.py
MIMICEmbedding/wave_preproc.py
MIMICEmbedding/mappings/__init__.py
MIMICEmbedding/mappings/diagnoses_icd.csv.gz
MIMICEmbedding/mappings/ecg_record_list.csv.gz
MIMICEmbedding/mappings/echo-record-list.csv.gz
MIMICEmbedding/mappings/mapped_cxr_studies.csv.gz
MIMICEmbedding/mappings/mimic-cxr-2.0.0-metadata.csv.gz
MIMICEmbedding/mappings/wave_record_list.csv.gz
mimicembedding-0.1.dist-info/licenses/LICENSE.txt
mimicembedding-0.1.dist-info/METADATA
mimicembedding-0.1.dist-info/WHEEL
mimicembedding-0.1.dist-info/top_level.txt
mimicembedding-0.1.dist-info/RECORD
