Metadata-Version: 2.4
Name: MIMICEmbedding
Version: 0.1
Summary: Cohort extraction and embedding for MIMIC-CXR, MIMIC-ECG, MIMIC-ECHO, MIMIC-Waveform
License-File: LICENSE.txt
Dynamic: license-file
